.gitignore
CHANGES.txt
CONTRIBUTORS.txt
COPYRIGHT.txt
LICENSE.txt
README.rst
TODO.txt
setup.cfg
setup.py
tox.ini
docs/.gitignore
docs/Makefile
docs/api.rst
docs/conf.py
docs/glossary.rst
docs/index.rst
docs/zcml.rst
docs/.static/logo_hi.gif
docs/.static/repoze.css
pyramid_handlers/__init__.py
pyramid_handlers/meta.zcml
pyramid_handlers/tests.py
pyramid_handlers/zcml.py
pyramid_handlers.egg-info/PKG-INFO
pyramid_handlers.egg-info/SOURCES.txt
pyramid_handlers.egg-info/dependency_links.txt
pyramid_handlers.egg-info/entry_points.txt
pyramid_handlers.egg-info/not-zip-safe
pyramid_handlers.egg-info/requires.txt
pyramid_handlers.egg-info/top_level.txt