Metadata-Version: 1.0
Name: pyramid-handlers
Version: 0.2
Summary: Pyramid handlers emulate Pylons 1 controllers
Home-page: http://docs.pylonsproject.org
Author: Chris McDonough, Agendaless Consulting
Author-email: pylons-devel@googlegroups.com
License: BSD-derived (http://www.repoze.org/LICENSE.txt)
Keywords: web wsgi pylons pyramid
Platform: UNKNOWN
Classifier: Intended Audience :: Developers
Classifier: Programming Language :: Python
Classifier: Framework :: Pylons
Classifier: Topic :: Internet :: WWW/HTTP
Classifier: Topic :: Internet :: WWW/HTTP :: WSGI
Classifier: License :: Repoze Public License
